LICENSE
README.md
setup.cfg
setup.py
POGREQ/__init__.py
POGREQ/faster_than_requests.nim
POGREQ/faster_than_requests.nim.cfg
POGREQ/gctricks.py
POGREQ/libcrypto-1_1-x64.dll
POGREQ/libcrypto-1_1.dll
POGREQ/libeay64.dll
POGREQ/pcre64.dll
POGREQ/sqlite3_64.dll
POGREQ/ssleay64.dll
POGREQ/ws.nim
thisisapogreq.egg-info/PKG-INFO
thisisapogreq.egg-info/SOURCES.txt
thisisapogreq.egg-info/dependency_links.txt
thisisapogreq.egg-info/requires.txt
thisisapogreq.egg-info/top_level.txt
thisisapogreq.egg-info/zip-safe