Metadata-Version: 2.1
Name: thisisapogreq
Version: 21.3.3
Summary: Faster & simpler requests replacement for Python
Home-page: https://github.com/juancarlospaco
Author: Juan Carlos
Author-email: juancarlospaco@gmail.com
License: MIT
Keywords: python3,python4,cpython,speed,cython,rust,wasm,c,performance,compiled,native,fast,nim,argentina,requests,httpx,httpie,scraper,scrapinghub,curl,wget,http,web,ssl,nimporter
Platform: Linux
Platform: Darwin
Platform: Windows
Classifier: Development Status :: 5 - Production/Stable
Classifier: Environment :: Console
Classifier: Environment :: Other Environment
Classifier: Intended Audience :: Developers
Classifier: Intended Audience :: Other Audience
Classifier: Natural Language :: English
Classifier: Operating System :: OS Independent
Classifier: Operating System :: POSIX :: Linux
Classifier: Operating System :: Microsoft :: Windows
Classifier: Operating System :: MacOS :: MacOS X
Classifier: Programming Language :: Python
Classifier: Programming Language :: Python :: 3
Classifier: Programming Language :: Python :: 3 :: Only
Classifier: Programming Language :: Python :: 3.6
Classifier: Programming Language :: Python :: 3.7
Classifier: Programming Language :: Python :: 3.8
Classifier: Programming Language :: Python :: 3.9
Classifier: Programming Language :: Python :: Implementation :: CPython
Classifier: Topic :: Software Development
Requires-Python: >=3.7
